my_matrix_module/__init__.py
my_matrix_module/matrix.py
my_matrix_module-0.1.dist-info/METADATA
my_matrix_module-0.1.dist-info/WHEEL
my_matrix_module-0.1.dist-info/top_level.txt
my_matrix_module-0.1.dist-info/RECORD
