Metadata-Version: 2.1
Name: my_matrix_module
Version: 0.1
Summary: A library for matrix operations with Fraction support
Home-page: https://github.com/ArturZZerg/matrix
Author: Artur Vakula
Author-email: artur.vakula@gmail.com
Classifier: Programming Language :: Python :: 3
Classifier: License :: OSI Approved :: MIT License
Classifier: Operating System :: OS Independent
Requires-Python: >=3.7
